Workbook

Sheet Premissas
A1: Yotakes — Planilha financeira
A2: Células amarelas são entradas. Todas as outras abas são fórmulas sobre esta. Preços e infraestrutura: memória de cálculo do deck (15/09/2026).
A4: Chave | B4: Premissa | C4: Valor | D4: Nota
A5: preco_sous | B5: Preço Sous Chef (R$/mês) | C5: 9.9 | D5: Logo acima do Letterboxd Pro (US$ 19/ano ≈ R$ 8,15/mês).
A6: preco_chef | B6: Preço Chef (R$/mês) | C6: 23.9 | D6: Igual ao Spotify Individual no Brasil; logo acima do Letterboxd Patron (≈ R$ 21,03/mês).
A7: preco_parceiro | B7: Preço Restaurante Parceiro — Analytics (R$/mês) | C7: 199 | D7: Hipótese. Abaixo do ReviewTrackers (a partir de US$ 89 ≈ R$ 458/mês) e muito abaixo do Birdeye (US$ 299–449). A validar com os pilotos.
A8: taxa_loja | B8: Taxa das lojas de aplicativo (B2C) | C8: 0.15 | D8: App Store / Google Play, Small Business Program (receita anual < US$ 1 mi).
A9: imposto | B9: Imposto sobre receita (Simples Nacional, faixa inicial) | C9: 0.06
A10: conv_sous | B10: Conversão para Sous Chef (% dos usuários ativos) | C10: 0.015 | D10: Conservador: o Letterboxd converte ~5% para planos pagos.
A11: conv_chef | B11: Conversão para Chef (% dos usuários ativos) | C11: 0.0075
A12: infra_base | B12: Infraestrutura básica até 10 mil usuários (R$/mês) | C12: 341 | D12: Banco + auth, hospedagem + CDN, e-mail transacional, mídia, domínio. Detalhe na aba Infraestrutura.
A13: infra_var | B13: Infraestrutura por usuário acima de 10 mil (R$/usuário/mês) | C13: 0.0074 | D13: Interpolação entre o cenário de 10 mil (R$ 341) e o de 100 mil (R$ 1.004).
A14: ia_parceiro | B14: IA do painel do parceiro (R$/parceiro/mês) | C14: 1.4 | D14: Modelo pequeno em lote semanal: ~US$ 0,0675 por análise × 4 semanas.
A15: servicos | B15: Monitoramento e serviços após o lançamento (R$/mês) | C15: 260 | D15: Observabilidade, e-mail acima da franquia, backups. Leva a infra à faixa de R$ 600 do deck.
A16: mkt_pre | B16: Marketing no beta fechado (R$/mês) | C16: 300 | D16: Material para convites, brindes para os primeiros avaliadores.
A17: mkt_pos | B17: Marketing após o lançamento (R$/mês) | C17: 1000 | D17: Conteúdo, ativações com creators, QR codes nos parceiros. Sem mídia paga.
A18: evento | B18: Evento de lançamento (R$, pontual) | C18: 3000 | D18: Lançamento oficial em restaurante parceiro, com menu exclusivo.
A19: juridico | B19: Jurídico e LGPD (R$, pontual) | C19: 2000 | D19: Termos de uso, política de privacidade e contrato padrão B2B.
A20: cambio | B20: Câmbio de referência (R$ por US$) | C20: 5.15 | D20: USD/BRL em 14/09/2026.

Sheet Preços
A1: Âncoras de preço e receita líquida por assinante
A3: Referência | B3: Base | C3: R$/mês
A4: Letterboxd Pro | B4: US$ 19/ano | C4: 8.15
A5: Sous Chef Yotakes | B5: mensal | C5: 9.9
A6: Duolingo Super (individual) | B6: mensal | C6: 14.99
A7: Netflix Padrão com anúncios | B7: mensal | C7: 20.9
A8: Letterboxd Patron | B8: US$ 49/ano | C8: 21.03
A9: Spotify Individual | B9: mensal | C9: 23.9
A10: Chef Yotakes | B10: mensal | C10: 23.9
A11: Duolingo Max | B11: mensal | C11: 33.33
A12: Netflix Padrão sem anúncios | B12: mensal | C12: 44.9
A15: Plano | B15: Preço bruto | C15: − Loja de apps | D15: − Imposto | E15: Receita líquida/mês
A16: Sous Chef | B16: =Premissas!$C$5 | C16: =B16*Premissas!$C$8 | D16: =(B16-C16)*Premissas!$C$9 | E16: =B16-C16-D16
A17: Chef | B17: =Premissas!$C$6 | C17: =B17*Premissas!$C$8 | D17: =(B17-C17)*Premissas!$C$9 | E17: =B17-C17-D17
A18: Restaurante Parceiro | B18: =Premissas!$C$7 | C18: 0 | D18: =(B18-C18)*Premissas!$C$9 | E18: =B18-C18-D18

Sheet Infraestrutura
A1: Custo de infraestrutura e ponto de equilíbrio
A3: Item — 10 mil usuários ativos/mês | B3: US$/mês | C3: R$/mês
A4: Banco de dados e autenticação (100 mil contas ativas inclusas) | B4: 25 | C4: 129
A5: Hospedagem e entrega de conteúdo (1 TB de tráfego) | B5: 20 | C5: 103
A6: E-mail transacional (acesso por link mágico e notificações) | B6: 20 | C6: 103
A7: Armazenamento das fotos dos takes (dentro da franquia) | B7: 0 | C7: 0
A8: Domínio e certificado (rateio mensal) | B8: 1.25 | C8: 6
A9: Total | B9: =SUM(B4:B8) | C9: =SUM(C4:C8)
A11: Item — 100 mil usuários ativos/mês | B11: US$/mês | C11: R$/mês
A12: Banco + autenticação e hospedagem + CDN (planos Pro) | B12: 45 | C12: =B12*Premissas!$C$20
A13: Armazenamento (≈ 420 GB médios, 100 GB inclusos) | B13: 6.72 | C13: =B13*Premissas!$C$20
A14: Tráfego acima do incluído (≈ 2,4 TB, cacheado a US$ 0,03/GB) | B14: 57 | C14: =B14*Premissas!$C$20
A15: E-mail transacional (volume maior) | B15: 85 | C15: =B15*Premissas!$C$20
A16: Domínio | B16: 1.25 | C16: =B16*Premissas!$C$20
A17: Total | B17: =SUM(B12:B16) | C17: =SUM(C12:C16)
A19: Ponto de equilíbrio | B19: Valor
A20: Custo por usuário/mês — 10 mil | B20: =Infraestrutura!$C$9/10000
A21: Custo por usuário/mês — 100 mil | B21: =Infraestrutura!$C$17/100000
A22: Chefs necessários — 10 mil (receita líquida) | B22: =ROUNDUP(Infraestrutura!$C$9/Preços!$E$17,0)
A23: Sous Chefs necessários — 10 mil (receita líquida) | B23: =ROUNDUP(Infraestrutura!$C$9/Preços!$E$16,0)
A24: Chefs necessários — 10 mil (preço bruto, como no deck) | B24: =ROUNDUP(Infraestrutura!$C$9/Premissas!$C$6,0)
A25: Sous Chefs necessários — 10 mil (preço bruto, como no deck) | B25: =ROUNDUP(Infraestrutura!$C$9/Premissas!$C$5,0)
A26: Chefs necessários — 100 mil (receita líquida) | B26: =ROUNDUP(Infraestrutura!$C$17/Preços!$E$17,0)
A27: % da base que precisa ser Chef — 10 mil | B27: =B22/10000
A28: Usuários gratuitos sustentados por Chef — 10 mil | B28: =10000/B22

Sheet IA do parceiro
A1: Custo da leitura por IA no painel do Restaurante Parceiro
A3: Item | B3: Valor | C3: Unidade
A4: Preço de entrada (US$ por milhão de tokens) | B4: 1 | C4: US$/M tokens
A5: Preço de saída (US$ por milhão de tokens) | B5: 5 | C5: US$/M tokens
A6: Tokens de entrada por análise | B6: 60000 | C6: tokens
A7: Tokens de saída por análise | B7: 1500 | C7: tokens
A8: Análises por mês (semanal) | B8: 4 | C8: análises
A9: Custo por análise (US$) | B9: =B4*B6/1000000+B5*B7/1000000 | C9: US$
A10: Custo por análise (R$) | B10: =B9*Premissas!$C$20 | C10: R$
A11: Custo por parceiro por mês (R$) | B11: =B10*B8 | C11: R$
A12: Referência de mercado — ReviewTrackers (a partir de, R$/mês) | B12: =89*Premissas!$C$20 | C12: R$
A13: Referência de mercado — Birdeye (de, R$/mês) | B13: =299*Premissas!$C$20 | C13: R$

Sheet Projeção
A1: Projeção de 12 meses — novembro de 2026 a outubro de 2027
A2: Entradas (amarelo): usuários ativos, parceiros, B2C monetizado (1/0), lançado (1/0) e pontuais. O resto é fórmula sobre Premissas e Preços.
A4: Mês | B4: Fase | C4: Usuários ativos | D4: Parceiros | E4: B2C monetizado | F4: Lançado | G4: Assinantes Sous Chef | H4: Assinantes Chef | I4: Receita B2C bruta | J4: Receita B2C líquida | K4: Receita B2B bruta | L4: Receita B2B líquida | M4: Receita líquida total | N4: Infraestrutura | O4: IA do parceiro | P4: Serviços | Q4: Marketing | R4: Pontuais | S4: Custos totais | T4: Resultado | U4: Caixa acumulado
A5: Nov/2026 | B5: Beta fechado | C5: 300 | D5: 0 | E5: 0 | F5: 0 | G5: =ROUND(C5*Premissas!$C$10*E5,0) | H5: =ROUND(C5*Premissas!$C$11*E5,0) | I5: =G5*Premissas!$C$5+H5*Premissas!$C$6 | J5: =I5*(1-Premissas!$C$8)*(1-Premissas!$C$9) | K5: =D5*Premissas!$C$7 | L5: =K5*(1-Premissas!$C$9) | M5: =J5+L5 | N5: =Premissas!$C$12+MAX(0,C5-10000)*Premissas!$C$13 | O5: =D5*Premissas!$C$14 | P5: =Premissas!$C$15*F5 | Q5: =IF(F5=1,Premissas!$C$17,Premissas!$C$16) | R5: 0 | S5: =SUM(N5:R5) | T5: =M5-S5 | U5: =T5
A6: Dez/2026 | B6: Beta fechado | C6: 500 | D6: 0 | E6: 0 | F6: 0 | G6: =ROUND(C6*Premissas!$C$10*E6,0) | H6: =ROUND(C6*Premissas!$C$11*E6,0) | I6: =G6*Premissas!$C$5+H6*Premissas!$C$6 | J6: =I6*(1-Premissas!$C$8)*(1-Premissas!$C$9) | K6: =D6*Premissas!$C$7 | L6: =K6*(1-Premissas!$C$9) | M6: =J6+L6 | N6: =Premissas!$C$12+MAX(0,C6-10000)*Premissas!$C$13 | O6: =D6*Premissas!$C$14 | P6: =Premissas!$C$15*F6 | Q6: =IF(F6=1,Premissas!$C$17,Premissas!$C$16) | R6: 0 | S6: =SUM(N6:R6) | T6: =M6-S6 | U6: =U5+T6
A7: Jan/2027 | B7: Beta fechado | C7: 800 | D7: 0 | E7: 0 | F7: 0 | G7: =ROUND(C7*Premissas!$C$10*E7,0) | H7: =ROUND(C7*Premissas!$C$11*E7,0) | I7: =G7*Premissas!$C$5+H7*Premissas!$C$6 | J7: =I7*(1-Premissas!$C$8)*(1-Premissas!$C$9) | K7: =D7*Premissas!$C$7 | L7: =K7*(1-Premissas!$C$9) | M7: =J7+L7 | N7: =Premissas!$C$12+MAX(0,C7-10000)*Premissas!$C$13 | O7: =D7*Premissas!$C$14 | P7: =Premissas!$C$15*F7 | Q7: =IF(F7=1,Premissas!$C$17,Premissas!$C$16) | R7: 2000 | S7: =SUM(N7:R7) | T7: =M7-S7 | U7: =U6+T7
A8: Fev/2027 | B8: Lançamento público | C8: 2000 | D8: 0 | E8: 0 | F8: 1 | G8: =ROUND(C8*Premissas!$C$10*E8,0) | H8: =ROUND(C8*Premissas!$C$11*E8,0) | I8: =G8*Premissas!$C$5+H8*Premissas!$C$6 | J8: =I8*(1-Premissas!$C$8)*(1-Premissas!$C$9) | K8: =D8*Premissas!$C$7 | L8: =K8*(1-Premissas!$C$9) | M8: =J8+L8 | N8: =Premissas!$C$12+MAX(0,C8-10000)*Premissas!$C$13 | O8: =D8*Premissas!$C$14 | P8: =Premissas!$C$15*F8 | Q8: =IF(F8=1,Premissas!$C$17,Premissas!$C$16) | R8: 3000 | S8: =SUM(N8:R8) | T8: =M8-S8 | U8: =U7+T8
A9: Mar/2027 | B9: Escala e monetização | C9: 3000 | D9: 2 | E9: 1 | F9: 1 | G9: =ROUND(C9*Premissas!$C$10*E9,0) | H9: =ROUND(C9*Premissas!$C$11*E9,0) | I9: =G9*Premissas!$C$5+H9*Premissas!$C$6 | J9: =I9*(1-Premissas!$C$8)*(1-Premissas!$C$9) | K9: =D9*Premissas!$C$7 | L9: =K9*(1-Premissas!$C$9) | M9: =J9+L9 | N9: =Premissas!$C$12+MAX(0,C9-10000)*Premissas!$C$13 | O9: =D9*Premissas!$C$14 | P9: =Premissas!$C$15*F9 | Q9: =IF(F9=1,Premissas!$C$17,Premissas!$C$16) | R9: 0 | S9: =SUM(N9:R9) | T9: =M9-S9 | U9: =U8+T9
A10: Abr/2027 | B10: Escala e monetização | C10: 4000 | D10: 4 | E10: 1 | F10: 1 | G10: =ROUND(C10*Premissas!$C$10*E10,0) | H10: =ROUND(C10*Premissas!$C$11*E10,0) | I10: =G10*Premissas!$C$5+H10*Premissas!$C$6 | J10: =I10*(1-Premissas!$C$8)*(1-Premissas!$C$9) | K10: =D10*Premissas!$C$7 | L10: =K10*(1-Premissas!$C$9) | M10: =J10+L10 | N10: =Premissas!$C$12+MAX(0,C10-10000)*Premissas!$C$13 | O10: =D10*Premissas!$C$14 | P10: =Premissas!$C$15*F10 | Q10: =IF(F10=1,Premissas!$C$17,Premissas!$C$16) | R10: 0 | S10: =SUM(N10:R10) | T10: =M10-S10 | U10: =U9+T10
A11: Mai/2027 | B11: Escala e monetização | C11: 5000 | D11: 6 | E11: 1 | F11: 1 | G11: =ROUND(C11*Premissas!$C$10*E11,0) | H11: =ROUND(C11*Premissas!$C$11*E11,0) | I11: =G11*Premissas!$C$5+H11*Premissas!$C$6 | J11: =I11*(1-Premissas!$C$8)*(1-Premissas!$C$9) | K11: =D11*Premissas!$C$7 | L11: =K11*(1-Premissas!$C$9) | M11: =J11+L11 | N11: =Premissas!$C$12+MAX(0,C11-10000)*Premissas!$C$13 | O11: =D11*Premissas!$C$14 | P11: =Premissas!$C$15*F11 | Q11: =IF(F11=1,Premissas!$C$17,Premissas!$C$16) | R11: 0 | S11: =SUM(N11:R11) | T11: =M11-S11 | U11: =U10+T11
A12: Jun/2027 | B12: Escala e monetização | C12: 6000 | D12: 8 | E12: 1 | F12: 1 | G12: =ROUND(C12*Premissas!$C$10*E12,0) | H12: =ROUND(C12*Premissas!$C$11*E12,0) | I12: =G12*Premissas!$C$5+H12*Premissas!$C$6 | J12: =I12*(1-Premissas!$C$8)*(1-Premissas!$C$9) | K12: =D12*Premissas!$C$7 | L12: =K12*(1-Premissas!$C$9) | M12: =J12+L12 | N12: =Premissas!$C$12+MAX(0,C12-10000)*Premissas!$C$13 | O12: =D12*Premissas!$C$14 | P12: =Premissas!$C$15*F12 | Q12: =IF(F12=1,Premissas!$C$17,Premissas!$C$16) | R12: 0 | S12: =SUM(N12:R12) | T12: =M12-S12 | U12: =U11+T12
A13: Jul/2027 | B13: Escala e monetização | C13: 7000 | D13: 10 | E13: 1 | F13: 1 | G13: =ROUND(C13*Premissas!$C$10*E13,0) | H13: =ROUND(C13*Premissas!$C$11*E13,0) | I13: =G13*Premissas!$C$5+H13*Premissas!$C$6 | J13: =I13*(1-Premissas!$C$8)*(1-Premissas!$C$9) | K13: =D13*Premissas!$C$7 | L13: =K13*(1-Premissas!$C$9) | M13: =J13+L13 | N13: =Premissas!$C$12+MAX(0,C13-10000)*Premissas!$C$13 | O13: =D13*Premissas!$C$14 | P13: =Premissas!$C$15*F13 | Q13: =IF(F13=1,Premissas!$C$17,Premissas!$C$16) | R13: 0 | S13: =SUM(N13:R13) | T13: =M13-S13 | U13: =U12+T13
A14: Ago/2027 | B14: Escala e monetização | C14: 8000 | D14: 13 | E14: 1 | F14: 1 | G14: =ROUND(C14*Premissas!$C$10*E14,0) | H14: =ROUND(C14*Premissas!$C$11*E14,0) | I14: =G14*Premissas!$C$5+H14*Premissas!$C$6 | J14: =I14*(1-Premissas!$C$8)*(1-Premissas!$C$9) | K14: =D14*Premissas!$C$7 | L14: =K14*(1-Premissas!$C$9) | M14: =J14+L14 | N14: =Premissas!$C$12+MAX(0,C14-10000)*Premissas!$C$13 | O14: =D14*Premissas!$C$14 | P14: =Premissas!$C$15*F14 | Q14: =IF(F14=1,Premissas!$C$17,Premissas!$C$16) | R14: 0 | S14: =SUM(N14:R14) | T14: =M14-S14 | U14: =U13+T14
A15: Set/2027 | B15: Escala e monetização | C15: 9000 | D15: 16 | E15: 1 | F15: 1 | G15: =ROUND(C15*Premissas!$C$10*E15,0) | H15: =ROUND(C15*Premissas!$C$11*E15,0) | I15: =G15*Premissas!$C$5+H15*Premissas!$C$6 | J15: =I15*(1-Premissas!$C$8)*(1-Premissas!$C$9) | K15: =D15*Premissas!$C$7 | L15: =K15*(1-Premissas!$C$9) | M15: =J15+L15 | N15: =Premissas!$C$12+MAX(0,C15-10000)*Premissas!$C$13 | O15: =D15*Premissas!$C$14 | P15: =Premissas!$C$15*F15 | Q15: =IF(F15=1,Premissas!$C$17,Premissas!$C$16) | R15: 0 | S15: =SUM(N15:R15) | T15: =M15-S15 | U15: =U14+T15
A16: Out/2027 | B16: Escala e monetização | C16: 10000 | D16: 20 | E16: 1 | F16: 1 | G16: =ROUND(C16*Premissas!$C$10*E16,0) | H16: =ROUND(C16*Premissas!$C$11*E16,0) | I16: =G16*Premissas!$C$5+H16*Premissas!$C$6 | J16: =I16*(1-Premissas!$C$8)*(1-Premissas!$C$9) | K16: =D16*Premissas!$C$7 | L16: =K16*(1-Premissas!$C$9) | M16: =J16+L16 | N16: =Premissas!$C$12+MAX(0,C16-10000)*Premissas!$C$13 | O16: =D16*Premissas!$C$14 | P16: =Premissas!$C$15*F16 | Q16: =IF(F16=1,Premissas!$C$17,Premissas!$C$16) | R16: 0 | S16: =SUM(N16:R16) | T16: =M16-S16 | U16: =U15+T16
A17: Total 12 meses | I17: =SUM(I5:I16) | J17: =SUM(J5:J16) | K17: =SUM(K5:K16) | L17: =SUM(L5:L16) | M17: =SUM(M5:M16) | N17: =SUM(N5:N16) | O17: =SUM(O5:O16) | P17: =SUM(P5:P16) | ... T17: =SUM(T5:T16)
A19: Indicador | B19: Valor
A20: Pior ponto do caixa (capital mínimo necessário) | B20: =MIN(U5:U16)
A21: Primeiro mês com resultado positivo | B21: =IFERROR(INDEX(A5:A16,MATCH(TRUE,INDEX(T5:T16>0,0),0)),"—")
A22: Receita líquida mensal em outubro de 2027 | B22: =M16
A23: Participação B2B na receita de outubro de 2027 | B23: =IF(M16=0,0,L16/M16)
A24: Resultado acumulado em 12 meses | B24: =T17
